JuejinPdudoSampleWeb/__init__.py
JuejinPdudoSampleWeb/myWeb.py
fengfengzhaopypitest-0.0.1.dist-info/licenses/LICENSE
fengfengzhaopypitest-0.0.1.dist-info/METADATA
fengfengzhaopypitest-0.0.1.dist-info/WHEEL
fengfengzhaopypitest-0.0.1.dist-info/top_level.txt
fengfengzhaopypitest-0.0.1.dist-info/RECORD
