Metadata-Version: 2.4
Name: fengfengZhaoPypiTest
Version: 0.0.1
Summary: A simple WSGI-compliant web application layer framework
Author-email: pdudo <1052558+pdudo@user.noreply.gitee.com>
Project-URL: Homepage, https://gitee.com/pdudo/golearn/blob/master/python/PackagingTesting
Project-URL: Bug Tracker, https://gitee.com/pdudo/golearn/issues
Classifier: Programming Language :: Python :: 3
Classifier: License :: OSI Approved :: MIT License
Classifier: Operating System :: OS Independent
Requires-Python: >=3.7
License-File: LICENSE
Dynamic: license-file
